yirifi_ops_auth/__init__.py
yirifi_ops_auth/client.py
yirifi_ops_auth/decorators.py
yirifi_ops_auth/exceptions.py
yirifi_ops_auth/local_user.py
yirifi_ops_auth/middleware.py
yirifi_ops_auth/models.py
yirifi_ops_auth/deeplink/__init__.py
yirifi_ops_auth/deeplink/blueprint.py
yirifi_ops_auth/deeplink/environment.py
yirifi_ops_auth/deeplink/federation.py
yirifi_ops_auth/deeplink/jinja.py
yirifi_ops_auth/deeplink/registry.py
yirifi_ops_auth/deeplink/resolver.py
yirifi_ops_auth/deeplink/yaml_loader.py
yirifi_ops_auth_client-3.2.6.dist-info/METADATA
yirifi_ops_auth_client-3.2.6.dist-info/WHEEL
yirifi_ops_auth_client-3.2.6.dist-info/top_level.txt
yirifi_ops_auth_client-3.2.6.dist-info/RECORD
