Metadata-Version: 2.4
Name: yirifi-ops-auth-client
Version: 3.2.6
Summary: Authentication client library for Yirifi Ops microsites with RBAC support
Requires-Python: >=3.10
Requires-Dist: httpx>=0.27
Requires-Dist: flask>=2.0
Requires-Dist: sqlalchemy>=2.0.45
Provides-Extra: yaml
Requires-Dist: pyyaml>=6.0; extra == "yaml"
Provides-Extra: dev
Requires-Dist: pytest>=8.0; extra == "dev"
Requires-Dist: pytest-cov>=4.0; extra == "dev"
Requires-Dist: responses>=0.24; extra == "dev"
Requires-Dist: pyyaml>=6.0; extra == "dev"
